Metadata-Version: 1.0
Name: loot
Version: 0.2.0
Summary: loot is a command line tool that helps you work with github without pain
Home-page: https://github.com/gaotongfei/loot
Author: Taff Gao
Author-email: gaotongfei199@gmail.com
License: UNKNOWN
Platform: UNKNOWN
